dockertools/__init__.py
dockertools/factory.py
dockertools/utils.py
dockertools/scripts/__init__.py
dockertools/scripts/build.py
dockertools/scripts/push.py
dockertools/scripts/push_pull.py
dockertools/test/__init__.py
dockertools-0.2.1.data/scripts/docker-build
dockertools-0.2.1.data/scripts/docker-pull
dockertools-0.2.1.data/scripts/docker-push
dockertools-0.2.1.dist-info/DESCRIPTION.rst
dockertools-0.2.1.dist-info/entry_points.txt
dockertools-0.2.1.dist-info/METADATA
dockertools-0.2.1.dist-info/pydist.json
dockertools-0.2.1.dist-info/RECORD
dockertools-0.2.1.dist-info/top_level.txt
dockertools-0.2.1.dist-info/WHEEL
