Metadata-Version: 2.0
Name: dockertools
Version: 0.2.1
Summary: Command line utilities to make working with Docker easier.
Home-page: https://github.com/GaretJax/dockertools
Author: Jonathan Stoppani
Author-email: jonathan@stoppani.name
License: MIT
Platform: UNKNOWN
Classifier: Development Status :: 4 - Beta
Classifier: Intended Audience :: Developers
Classifier: License :: OSI Approved :: MIT License
Classifier: Operating System :: OS Independent
Classifier: Programming Language :: Python
Classifier: Topic :: Software Development :: Libraries :: Python Modules
Requires-Dist: docker-py (==0.4.0)
Requires-Dist: mock (==1.0.1)
Requires-Dist: requests (==2.2.1)
Requires-Dist: six (>=1.3.0)
Requires-Dist: websocket-client (==0.11.0)
Requires-Dist: click (==3.1)
Requires-Dist: dnspython (==1.11.1)
